smart_encryptor/__init__.py
smart_encryptor/core.py
smart_encryptor/keygen.py
smart_encryptor/keymanager.py
smart_encryptor-1.0.0.dist-info/licenses/LICENSE
smart_encryptor-1.0.0.dist-info/METADATA
smart_encryptor-1.0.0.dist-info/WHEEL
smart_encryptor-1.0.0.dist-info/top_level.txt
smart_encryptor-1.0.0.dist-info/RECORD
