Metadata-Version: 2.4
Name: smart-encryptor
Version: 1.0.0
Summary: A secure AES-256-GCM based encryption/decryption library with default key support.
Author-email: Rejith Kumar Rasal <rejithsham296@outlook.com>
Project-URL: Homepage, https://bitbucket.org/RejithkumarIT/pypi-packages/src/develop/smart-encryptor
Project-URL: Repository, https://bitbucket.org/RejithkumarIT/pypi-packages/src/develop/smart-encryptor
Project-URL: Issues, https://bitbucket.org/RejithkumarIT/pypi-packages/src/develop/smart-encryptor/issues
Keywords: encryption,security,aes,cryptography,secure,key,python,cipher
Classifier: Programming Language :: Python :: 3
Classifier: Topic :: Security :: Cryptography
Classifier: License :: OSI Approved :: MIT License
Classifier: Operating System :: OS Independent
Requires-Python: >=3.8
License-File: LICENSE
Requires-Dist: cryptography>=42.0.0
Dynamic: license-file
